SP_LICENSE
defsetup.py
distribute_setup.py
setup.cfg
setup.py
doc/README
lib/opuscoords/__init__.py
lib/opuscoords/version.py
lib/opuscoords.egg-info/PKG-INFO
lib/opuscoords.egg-info/SOURCES.txt
lib/opuscoords.egg-info/dependency_links.txt
lib/opuscoords.egg-info/not-zip-safe
lib/opuscoords.egg-info/requires.txt
lib/opuscoords.egg-info/top_level.txt
src/GCcoords_module.c
src/gc_coords_pkg.c
src/gc_coords_private.h
src/gc_opus_private.h