Metadata-Version: 1.1
Name: opuscoords
Version: 1.0.1
Summary: Python Tools for OPUS Coordinate Conversions
Home-page: http://www.stsci.edu/resources/software_hardware/stsci_python
Author: Warren Hack
Author-email: help@stsci.edu
License: UNKNOWN
Platform: UNKNOWN
Classifier: Intended Audience :: Science/Research
Classifier: License :: OSI Approved :: BSD License
Classifier: Operating System :: OS Independent
Classifier: Programming Language :: Python
Classifier: Topic :: Scientific/Engineering :: Astronomy
Classifier: Topic :: Software Development :: Libraries :: Python Modules
